SandV/ALU.v
module ALU (
    input [3:0] A, B,
    input [2:0] opcode,
    input clk,
    output reg [3:0] result,
    output reg carry_out
);

    always @(posedge clk) begin
        carry_out = 0; // Reset carry_out
        case (opcode)
            3'b000: {carry_out, result} = A + B;          // Addition
            3'b001: {carry_out, result} = A - B;          // Subtraction
            3'b010: result = A * B;                       // Multiplication
            3'b011: result = (B != 0) ? A / B : 4'b0000;  // Division with zero handling
            3'b100: result = A & B;                       // AND
            3'b101: result = A | B;                       // OR
            3'b110: result = ~A;                          // NOT
            default: result = 4'b0000;                    // Default case
        endcase
    end

endmodule

SandV/ALU_TB.v
module ALU_TB;

    reg [3:0] A, B;
    reg [2:0] opcode;
    reg clk;
    wire [3:0] result;
    wire carry_out;

    // Instantiate the ALU
    ALU uut (
        .A(A),
        .B(B),
        .opcode(opcode),
        .clk(clk),
        .result(result),
        .carry_out(carry_out)
    );

    // Clock generation
    initial begin
        clk = 0;
        forever #5 clk = ~clk; // 10-time unit clock period
    end

    // Test stimulus
    initial begin
        $dumpfile("ALU.vcd");
        $dumpvars(0, ALU_TB);
        $display("Testing Clocked 4-bit ALU...");
        $display("Opcode | A (Dec) | B (Dec) | Result (Dec) | Carry Out");

        // Test addition
        A = 4'b0011; B = 4'b0101; opcode = 3'b000; #10;
        $display("  ADD  | %d       | %d       | %d            | %b", A, B, result, carry_out);

        // Test subtraction
        A = 4'b1001; B = 4'b0011; opcode = 3'b001; #10;
        $display("  SUB  | %d       | %d       | %d            | %b", A, B, result, carry_out);

        // Test multiplication
        A = 4'b0010; B = 4'b0011; opcode = 3'b010; #10;
        $display("  MUL  | %d       | %d       | %d            | %b", A, B, result, carry_out);

        // Test division
        A = 4'b1000; B = 4'b0010; opcode = 3'b011; #10;
        $display("  DIV  | %d       | %d       | %d            | %b", A, B, result, carry_out);

        // Test AND
        A = 4'b1010; B = 4'b1100; opcode = 3'b100; #10;
        $display("  AND  | %d       | %d       | %d            | %b", A, B, result, carry_out);

        // Test OR
        A = 4'b1010; B = 4'b0101; opcode = 3'b101; #10;
        $display("  OR   | %d       | %d       | %d            | %b", A, B, result, carry_out);

        // Test NOT
        A = 4'b1010; opcode = 3'b110; #10;
        $display("  NOT  | %d       | -        | %d            | %b", A, result, carry_out);

        $display("Test complete.");
        $finish;
    end
endmodule

SandV/ALU.vcd
$date
	Tue Feb 25 11:17:54 2025
$end
$version
	Icarus Verilog
$end
$timescale
	1s
$end
$scope module ALU_TB $end
$var wire 4 ! result [3:0] $end
$var wire 1 " carry_out $end
$var reg 4 # A [3:0] $end
$var reg 4 $ B [3:0] $end
$var reg 1 % clk $end
$var reg 3 & opcode [2:0] $end
$scope module uut $end
$var wire 4 ' A [3:0] $end
$var wire 4 ( B [3:0] $end
$var wire 1 % clk $end
$var wire 3 ) opcode [2:0] $end
$var reg 1 " carry_out $end
$var reg 4 * result [3:0] $end
$upscope $end
$upscope $end
$enddefinitions $end
$comment Show the parameter values. $end
$dumpall
$end
#0
$dumpvars
bx *
b0 )
b101 (
b11 '
b0 &
0%
b101 $
b11 #
x"
bx !
$end
#5
b1000 !
b1000 *
0"
1%
#10
0%
b1 &
b1 )
b11 $
b11 (
b1001 #
b1001 '
#15
b110 !
b110 *
1%
#20
0%
b10 &
b10 )
b10 #
b10 '
#25
1%
#30
0%
b11 &
b11 )
b10 $
b10 (
b1000 #
b1000 '
#35
b100 !
b100 *
1%
#40
0%
b100 &
b100 )
b1100 $
b1100 (
b1010 #
b1010 '
#45
b1000 !
b1000 *
1%
#50
0%
b101 &
b101 )
b101 $
b101 (
#55
b1111 !
b1111 *
1%
#60
0%
b110 &
b110 )
#65
b101 !
b101 *
1%
